README.md
setup.py
Markdown_Toolbox/__init__.py
Markdown_Toolbox/requirements.txt
Markdown_Toolbox/style.css
Markdown_Toolbox/test.py
Markdown_Toolbox.egg-info/PKG-INFO
Markdown_Toolbox.egg-info/SOURCES.txt
Markdown_Toolbox.egg-info/dependency_links.txt
Markdown_Toolbox.egg-info/entry_points.txt
Markdown_Toolbox.egg-info/requires.txt
Markdown_Toolbox.egg-info/top_level.txt
Markdown_Toolbox/misc/icon.icns
Markdown_Toolbox/misc/icon.ico
Markdown_Toolbox/misc/sponsor.jpg
Markdown_Toolbox/misc/Docs/README_zh.html
Markdown_Toolbox/moduels/component/NormalValue.py
Markdown_Toolbox/moduels/component/SponsorDialog.py
Markdown_Toolbox/moduels/component/Stream.py
Markdown_Toolbox/moduels/component/Widget_FileLineEdit.py
Markdown_Toolbox/moduels/component/Widget_FileList.py
Markdown_Toolbox/moduels/component/Widget_StdoutBox.py
Markdown_Toolbox/moduels/function/checkDirectoryPath.py
Markdown_Toolbox/moduels/function/downloadFileFromUrl.py
Markdown_Toolbox/moduels/function/getAllUrlFromString.py
Markdown_Toolbox/moduels/function/getFileNameFromUrl.py
Markdown_Toolbox/moduels/function/getHumanReadableFileSize.py
Markdown_Toolbox/moduels/function/localizeLinksInDocument.py
Markdown_Toolbox/moduels/function/processHeaders.py
Markdown_Toolbox/moduels/function/restoreLinkFromJump.py
Markdown_Toolbox/moduels/gui/MainWindow.py
Markdown_Toolbox/moduels/gui/SystemTray.py
Markdown_Toolbox/moduels/gui/Tab_ClearAttatchment.py
Markdown_Toolbox/moduels/gui/Tab_Config.py
Markdown_Toolbox/moduels/gui/Tab_CopyMdFile.py
Markdown_Toolbox/moduels/gui/Tab_Help.py
Markdown_Toolbox/moduels/gui/Tab_LocalizeMdFile.py
Markdown_Toolbox/moduels/gui/Tab_Stdout.py
Markdown_Toolbox/moduels/thread/Thread_ClearAttatchment.py
Markdown_Toolbox/moduels/thread/Thread_LocalizeMdFile.py
Markdown_Toolbox/moduels/thread/Thread_TransportFile.py
Markdown_Toolbox/misc/icon.icns
Markdown_Toolbox/misc/icon.ico
Markdown_Toolbox/misc/sponsor.jpg
Markdown_Toolbox/misc/Docs/README_zh.html
Markdown_Toolbox/moduels/component/NormalValue.py
Markdown_Toolbox/moduels/component/SponsorDialog.py
Markdown_Toolbox/moduels/component/Stream.py
Markdown_Toolbox/moduels/component/Widget_FileLineEdit.py
Markdown_Toolbox/moduels/component/Widget_FileList.py
