Metadata-Version: 2.1
Name: Markdown-Toolbox
Version: 0.0.9
Summary: 一Markdown 工具箱，是我为 Markdown 笔记管理做的一个工具集。
Home-page: https://github.com/HaujetZhao/Markdown-Toolbox
Author: Haujet Zhao
Author-email: 1292756898@qq.com
Maintainer: Haujet Zhao
Maintainer-email: 1292756898@qq.com
License: MPL-2.0 License
Platform: all
Classifier: Development Status :: 4 - Beta
Classifier: Intended Audience :: End Users/Desktop
Classifier: Topic :: Documentation
Classifier: License :: OSI Approved :: Mozilla Public License 2.0 (MPL 2.0)
Classifier: Programming Language :: Python :: 3
Classifier: Programming Language :: Python :: 3.5
Classifier: Programming Language :: Python :: 3.6
Classifier: Programming Language :: Python :: 3.7
Classifier: Programming Language :: Python :: 3.8
Classifier: Programming Language :: Python :: 3 :: Only
Requires-Python: >=3.5, <4
